n_observer/__init__.py
n_observer/core.py
n_observer-0.1.0.dist-info/METADATA
n_observer-0.1.0.dist-info/WHEEL
n_observer-0.1.0.dist-info/top_level.txt
n_observer-0.1.0.dist-info/RECORD
