Metadata-Version: 2.4
Name: n-observer
Version: 0.1.0
Summary: An async/await observer pattern implementation. Supports observing multiple publishers from a single observer.
Author: N-Observer Contributors
Classifier: Programming Language :: Python :: 3
Classifier: Programming Language :: Python :: 3 :: Only
Classifier: Operating System :: OS Independent
Requires-Python: >=3.10
Requires-Dist: async_rwlock
Requires-Dist: typing_extensions
Provides-Extra: test
Requires-Dist: pytest; extra == "test"
Requires-Dist: pytest-asyncio; extra == "test"
